Schematics/testVerilog/module.v
// Verilog module auto-generated for AGC module A1 by dumbVerilog.py

module A1 ( 
  rst, FS01_, F02A, F02B, FS02, FS02A
);

input wire rst, FS01_;

output wire F02A, F02B, FS02, FS02A;

assign FS02A = rst ? 0 : ~(0|U126Pad7);
assign FS02 = rst ? 0 : ~(0|U126Pad7|U127Pad8);
assign U127Pad8 = rst ? 1 : ~(0|F02B|FS01_|U127Pad2);
assign U126Pad7 = rst ? 1 : ~(0|U127Pad2|FS02);
assign U127Pad2 = rst ? 0 : ~(0|U127Pad8|FS01_|F02A);
assign F02A = rst ? 0 : ~(0|U126Pad7|U127Pad2);
assign F02B = rst ? 0 : ~(0|U127Pad8|FS02);

endmodule

Schematics/testVerilog/module_tb.v
// Test bench for testVerilog.v
`timescale 1us / 1ns

module testVerilog;

reg rst = 1;
initial begin
  $dumpfile("testVerilog.vcd");
  $dumpvars(0, testVerilog);
  
  # 2 rst = 0;
  # 500 $finish;
end
  
reg FS01_ = 0;
always #4.883 FS01_ = !FS01_;
  
wire F02A, F02B, FS02, FS02A;
A1 A1A ( 
  rst, FS01_, F02A, F02B, FS02, FS02A
);
  
initial
  $timeformat(-6, 0, " us", 10);
initial
  $monitor("At time %t, rst=%d, FS01_=%d, F02B=%d, FS02=%d, FS02A=%d, FS02A=%d", $time, rst, FS01_, F02B, FS02, F02A, FS02A);

endmodule

Schematics/testVerilog/module.vcd
$date
	Wed Sep 26 15:18:59 2018
$end
$version
	Icarus Verilog
$end
$timescale
	1ns
$end
$scope module testVerilog $end
$var wire 1 ! FS02A $end
$var wire 1 " FS02 $end
$var wire 1 # F02B $end
$var wire 1 $ F02A $end
$var reg 1 % FS01_ $end
$var reg 1 & rst $end
$scope module A1A $end
$var wire 1 % FS01_ $end
$var wire 1 & rst $end
$var wire 1 ' U127Pad8 $end
$var wire 1 ( U127Pad2 $end
$var wire 1 ) U126Pad7 $end
$var wire 1 ! FS02A $end
$var wire 1 " FS02 $end
$var wire 1 # F02B $end
$var wire 1 $ F02A $end
$upscope $end
$upscope $end
$enddefinitions $end
#0
$dumpvars
1)
0(
1'
1&
0%
0$
0#
0"
0!
$end
#2000
0&
#4883
1#
0'
1%
#9766
0#
1"
1!
0)
1(
0%
#14649
1$
0(
1%
#19532
0$
0!
1)
0"
1'
0%
#24415
1#
0'
1%
#29298
0#
1"
1!
0)
1(
0%
#34181
1$
0(
1%
#39064
0$
0!
1)
0"
1'
0%
#43947
1#
0'
1%
#48830
0#
1"
1!
0)
1(
0%
#53713
1$
0(
1%
#58596
0$
0!
1)
0"
1'
0%
#63479
1#
0'
1%
#68362
0#
1"
1!
0)
1(
0%
#73245
1$
0(
1%
#78128
0$
0!
1)
0"
1'
0%
#83011
1#
0'
1%
#87894
0#
1"
1!
0)
1(
0%
#92777
1$
0(
1%
#97660
0$
0!
1)
0"
1'
0%
#102543
1#
0'
1%
#107426
0#
1"
1!
0)
1(
0%
#112309
1$
0(
1%
#117192
0$
0!
1)
0"
1'
0%
#122075
1#
0'
1%
#126958
0#
1"
1!
0)
1(
0%
#131841
1$
0(
1%
#136724
0$
0!
1)
0"
1'
0%
#141607
1#
0'
1%
#146490
0#
1"
1!
0)
1(
0%
#151373
1$
0(
1%
#156256
0$
0!
1)
0"
1'
0%
#161139
1#
0'
1%
#166022
0#
1"
1!
0)
1(
0%
#170905
1$
0(
1%
#175788
0$
0!
1)
0"
1'
0%
#180671
1#
0'
1%
#185554
0#
1"
1!
0)
1(
0%
#190437
1$
0(
1%
#195320
0$
0!
1)
0"
1'
0%
#200203
1#
0'
1%
#205086
0#
1"
1!
0)
1(
0%
#209969
1$
0(
1%
#214852
0$
0!
1)
0"
1'
0%
#219735
1#
0'
1%
#224618
0#
1"
1!
0)
1(
0%
#229501
1$
0(
1%
#234384
0$
0!
1)
0"
1'
0%
#239267
1#
0'
1%
#244150
0#
1"
1!
0)
1(
0%
#249033
1$
0(
1%
#253916
0$
0!
1)
0"
1'
0%
#258799
1#
0'
1%
#263682
0#
1"
1!
0)
1(
0%
#268565
1$
0(
1%
#273448
0$
0!
1)
0"
1'
0%
#278331
1#
0'
1%
#283214
0#
1"
1!
0)
1(
0%
#288097
1$
0(
1%
#292980
0$
0!
1)
0"
1'
0%
#297863
1#
0'
1%
#302746
0#
1"
1!
0)
1(
0%
#307629
1$
0(
1%
#312512
0$
0!
1)
0"
1'
0%
#317395
1#
0'
1%
#322278
0#
1"
1!
0)
1(
0%
#327161
1$
0(
1%
#332044
0$
0!
1)
0"
1'
0%
#336927
1#
0'
1%
#341810
0#
1"
1!
0)
1(
0%
#346693
1$
0(
1%
#351576
0$
0!
1)
0"
1'
0%
#356459
1#
0'
1%
#361342
0#
1"
1!
0)
1(
0%
#366225
1$
0(
1%
#371108
0$
0!
1)
0"
1'
0%
#375991
1#
0'
1%
#380874
0#
1"
1!
0)
1(
0%
#385757
1$
0(
1%
#390640
0$
0!
1)
0"
1'
0%
#395523
1#
0'
1%
#400406
0#
1"
1!
0)
1(
0%
#405289
1$
0(
1%
#410172
0$
0!
1)
0"
1'
0%
#415055
1#
0'
1%
#419938
0#
1"
1!
0)
1(
0%
#424821
1$
0(
1%
#429704
0$
0!
1)
0"
1'
0%
#434587
1#
0'
1%
#439470
0#
1"
1!
0)
1(
0%
#444353
1$
0(
1%
#449236
0$
0!
1)
0"
1'
0%
#454119
1#
0'
1%
#459002
0#
1"
1!
0)
1(
0%
#463885
1$
0(
1%
#468768
0$
0!
1)
0"
1'
0%
#473651
1#
0'
1%
#478534
0#
1"
1!
0)
1(
0%
#483417
1$
0(
1%
#488300
0$
0!
1)
0"
1'
0%
#493183
1#
0'
1%
#498066
0#
1"
1!
0)
1(
0%
