Schematics/testVerilog/testVerilog.v
// Verilog module auto-generated for AGC module A1 by dumbVerilog.py
module A1 ( 
  rst,
  FS01_,
  F02B,
  FS02,
  F02A,
  FS02A
);
input wire rst;
input wire FS01_;
output wire F02B;
output wire FS02;
output wire F02A;
output wire FS02A;

assign FS02A = ~(rst|U126Pad7);
assign FS02 = ~(rst|U126Pad7|U127Pad8);
assign U127Pad8 = ~(rst|F02B|FS01_|U127Pad2);
assign U126Pad7 = ~(rst|U127Pad2|FS02);
assign U127Pad2 = ~(rst|U127Pad8|FS01_|F02A);
assign F02A = ~(rst|U126Pad7|U127Pad2);
assign F02B = ~(rst|U127Pad8|FS02);

endmodule

Schematics/testVerilog/testVerilog_tb.v
// Test bench for testVerilog.v

module testVerilog;

  reg rst = 1;
  initial begin
    $dumpfile("testVerilog.vcd");
    $dumpvars(0, testVerilog);
    
    # 0 rst = 0;
    # 70 $finish;
  end
  
  reg FS01_ = 0;
  always #1 FS01_ = !FS01_;
  
  wire F02B;
  wire FS02;
  wire F02A;
  wire FS02A;
  A1 A1A (rst, FS01_, F02B, FS02, F02A, FS02A);
  
  initial
    $monitor("At time %t, rst=%d, FS01_=%d, F02B=%d, FS02=%d, FS02A=%d, FS02A=%d", $time, rst, FS01_, F02B, FS02, F02A, FS02A);

endmodule

Schematics/testVerilog/testVerilog.vcd
$date
	Wed Sep 26 08:22:34 2018
$end
$version
	Icarus Verilog
$end
$timescale
	1s
$end
$scope module testVerilog $end
$var wire 1 ! FS02A $end
$var wire 1 " FS02 $end
$var wire 1 # F02B $end
$var wire 1 $ F02A $end
$var reg 1 % FS01_ $end
$var reg 1 & rst $end
$scope module A1A $end
$var wire 1 $ F02A $end
$var wire 1 # F02B $end
$var wire 1 % FS01_ $end
$var wire 1 " FS02 $end
$var wire 1 ! FS02A $end
$var wire 1 ' U126Pad7 $end
$var wire 1 ( U127Pad2 $end
$var wire 1 ) U127Pad8 $end
$var wire 1 & rst $end
$upscope $end
$upscope $end
$enddefinitions $end
#0
$dumpvars
1)
0(
1'
0&
0%
0$
0#
0"
0!
$end
#1
1#
0)
1%
#2
0#
1"
1!
0'
1(
0%
#3
1$
0(
1%
#4
0$
0!
1'
0"
1)
0%
#5
1#
0)
1%
#6
0#
1"
1!
0'
1(
0%
#7
1$
0(
1%
#8
0$
0!
1'
0"
1)
0%
#9
1#
0)
1%
#10
0#
1"
1!
0'
1(
0%
#11
1$
0(
1%
#12
0$
0!
1'
0"
1)
0%
#13
1#
0)
1%
#14
0#
1"
1!
0'
1(
0%
#15
1$
0(
1%
#16
0$
0!
1'
0"
1)
0%
#17
1#
0)
1%
#18
0#
1"
1!
0'
1(
0%
#19
1$
0(
1%
#20
0$
0!
1'
0"
1)
0%
#21
1#
0)
1%
#22
0#
1"
1!
0'
1(
0%
#23
1$
0(
1%
#24
0$
0!
1'
0"
1)
0%
#25
1#
0)
1%
#26
0#
1"
1!
0'
1(
0%
#27
1$
0(
1%
#28
0$
0!
1'
0"
1)
0%
#29
1#
0)
1%
#30
0#
1"
1!
0'
1(
0%
#31
1$
0(
1%
#32
0$
0!
1'
0"
1)
0%
#33
1#
0)
1%
#34
0#
1"
1!
0'
1(
0%
#35
1$
0(
1%
#36
0$
0!
1'
0"
1)
0%
#37
1#
0)
1%
#38
0#
1"
1!
0'
1(
0%
#39
1$
0(
1%
#40
0$
0!
1'
0"
1)
0%
#41
1#
0)
1%
#42
0#
1"
1!
0'
1(
0%
#43
1$
0(
1%
#44
0$
0!
1'
0"
1)
0%
#45
1#
0)
1%
#46
0#
1"
1!
0'
1(
0%
#47
1$
0(
1%
#48
0$
0!
1'
0"
1)
0%
#49
1#
0)
1%
#50
0#
1"
1!
0'
1(
0%
#51
1$
0(
1%
#52
0$
0!
1'
0"
1)
0%
#53
1#
0)
1%
#54
0#
1"
1!
0'
1(
0%
#55
1$
0(
1%
#56
0$
0!
1'
0"
1)
0%
#57
1#
0)
1%
#58
0#
1"
1!
0'
1(
0%
#59
1$
0(
1%
#60
0$
0!
1'
0"
1)
0%
#61
1#
0)
1%
#62
0#
1"
1!
0'
1(
0%
#63
1$
0(
1%
#64
0$
0!
1'
0"
1)
0%
#65
1#
0)
1%
#66
0#
1"
1!
0'
1(
0%
#67
1$
0(
1%
#68
0$
0!
1'
0"
1)
0%
#69
1#
0)
1%
#70
0#
1"
1!
0'
1(
0%
